README.md
setup.py
src/example_package_dw/__init__.py
src/example_package_dw/example.py
src/example_package_dw.egg-info/PKG-INFO
src/example_package_dw.egg-info/SOURCES.txt
src/example_package_dw.egg-info/dependency_links.txt
src/example_package_dw.egg-info/top_level.txt