Metadata-Version: 1.0
Name: example-package-dw
Version: 0.0.1
Summary: Example package from DW
Home-page: http://packages.python.org/example_package_dw
Author: DW Shin
Author-email: dongwookshin@hotmail.com
License: UNKNOWN
Keywords: example python package
Platform: UNKNOWN
